pyideai/__init__.py
pyideai/main.py
pyideai-0.1.0.dist-info/METADATA
pyideai-0.1.0.dist-info/WHEEL
pyideai-0.1.0.dist-info/top_level.txt
pyideai-0.1.0.dist-info/RECORD
