Metadata-Version: 2.1
Name: pyideai
Version: 0.1.0
Summary: A module to interact with ideai.dev using Selenium WebDriver.
Home-page: https://gitlab.com/mutkuoz/pyideai
Author: Mehmet Utku ÖZTÜRK
Author-email: mutkuoz@proton.me
Classifier: Programming Language :: Python :: 3
Classifier: License :: OSI Approved :: MIT License
Classifier: Operating System :: OS Independent
Requires-Python: >=3.6
Requires-Dist: selenium
Requires-Dist: beautifulsoup4
Requires-Dist: webdriver-manager
